Metadata-Version: 2.1
Name: pypacking
Version: 0.0.2
Summary: Python packaging made easy
Home-page: https://pypi.org/project/pypacking
Author: Fulan@ de Tal
Author-email: fulano.de.tal@macondo.co
License: MIT
Keywords: Python Package
Classifier: Programming Language :: Python :: 3
Classifier: License :: OSI Approved :: MIT License
Classifier: Operating System :: OS Independent
License-File: LICENSE
Requires-Dist: numpy
